pysigning/__init__.py
pysigning-0.1.0.dist-info/LICENSE
pysigning-0.1.0.dist-info/WHEEL
pysigning-0.1.0.dist-info/METADATA
pysigning-0.1.0.dist-info/RECORD
